tboard_read/__init__.py
tboard_read/tboard_read.py
thunderboard_reader-0.1.2.data/scripts/tboard_read.py
thunderboard_reader-0.1.2.dist-info/LICENSE
thunderboard_reader-0.1.2.dist-info/METADATA
thunderboard_reader-0.1.2.dist-info/WHEEL
thunderboard_reader-0.1.2.dist-info/top_level.txt
thunderboard_reader-0.1.2.dist-info/RECORD
